MANIFEST.in
README.md
setup.py
audit_trail/__init__.py
audit_trail/admin.py
audit_trail/app.py
audit_trail/forms.py
audit_trail/models.py
audit_trail/signals.py
audit_trail/stringifier.py
audit_trail/utils.py
audit_trail/views.py
audit_trail/watcher.py
audit_trail/locale/ru/LC_MESSAGES/django.mo
audit_trail/locale/ru/LC_MESSAGES/django.po
audit_trail/migrations/0001_initial.py
audit_trail/migrations/0002_auto_20150112_1228.py
audit_trail/migrations/0003_auto_20150112_1236.py
audit_trail/migrations/0004_auto_20150112_1321.py
audit_trail/migrations/0005_auto_20150114_1622.py
audit_trail/migrations/0006_auto_20150124_0822.py
audit_trail/migrations/0007_auto_20150422_0548.py
audit_trail/migrations/0008_auto_20150824_1934.py
audit_trail/migrations/__init__.py
audit_trail/south_migrations/0001_initial.py
audit_trail/south_migrations/0002_auto__chg_field_audittrail_user_ip.py
audit_trail/south_migrations/__init__.py
audit_trail/templates/admin/audit_trail/audittrail/change_form.html
audit_trail/templates/audit_trail/change_row.html
audit_trail/templates/audit_trail/changes.html
django_audit_trail.egg-info/PKG-INFO
django_audit_trail.egg-info/SOURCES.txt
django_audit_trail.egg-info/dependency_links.txt
django_audit_trail.egg-info/requires.txt
django_audit_trail.egg-info/top_level.txt