Metadata-Version: 1.0
Name: django-audit-trail
Version: 0.1.23
Summary: App for tracking django model changes
Home-page: https://github.com/TriplePoint-Software/django_audit_trail
Author: Max Syabro
Author-email: maxim@syabro.com
License: Apache License, Version 2.0
Platform: UNKNOWN
